[
	{
		"MoveID": 1,
		"Accuracy": 100,
		"Power": 40,
		"PP": 35,
		"Priority": 0,
		"CriticalLevel": 0,
		"Target": 2,
		"Type": 0,
		"EffectInfos": [],
		"innerName": "Pound",
		"Category": 2,
		"MustHit": false
	},
	{
		"MoveID": 5,
		"Accuracy": 85,
		"Power": 80,
		"PP": 15,
		"Priority": 0,
		"CriticalLevel": 0,
		"Target": 2,
		"Type": 0,
		"EffectInfos": [],
		"innerName": "Mega Punch",
		"Category": 2,
		"MustHit": false
	},
	{
		"MoveID": 7,
		"Accuracy": 100,
		"Power": 75,
		"PP": 15,
		"Priority": 0,
		"CriticalLevel": 0,
		"Target": 2,
		"Type": 9,
		"EffectInfos": [],
		"innerName": "Fire Punch",
		"Category": 2,
		"MustHit": false
	},
	{
		"MoveID": 16,
		"Accuracy": 100,
		"Power": 40,
		"PP": 35,
		"Priority": 0,
		"CriticalLevel": 0,
		"Target": 2,
		"Type": 2,
		"EffectInfos": [],
		"innerName": "Gust",
		"Category": 3,
		"MustHit": false
	},
	{
		"MoveID": 17,
		"Accuracy": 100,
		"Power": 60,
		"PP": 35,
		"Priority": 0,
		"CriticalLevel": 0,
		"Target": 2,
		"Type": 2,
		"EffectInfos": [],
		"innerName": "Wing Attack",
		"Category": 3,
		"MustHit": false
	},
	{
		"MoveID": 22,
		"Accuracy": 100,
		"Power": 10,
		"PP": 25,
		"Priority": 0,
		"CriticalLevel": 0,
		"Target": 2,
		"Type": 11,
		"EffectInfos": [
		{
			"EffectID":3,
			"EffectChance":1,
			"Target":2
		}
		],
		"innerName": "VineWhip",
		"Category": 2,
		"MustHit": false
	},
	{
		"MoveID": 23,
		"Accuracy": 65,
		"Power": 100,
		"PP": 20,
		"Priority": 0,
		"CriticalLevel": 0,
		"Target": 2,
		"Type": 0,
		"EffectInfos": [],
		"innerName": "Stomp",
		"Category": 2,
		"MustHit": false
	},
	{
		"MoveID": 24,
		"Accuracy": 100,
		"Power": 30,
		"PP": 30,
		"Priority": 0,
		"CriticalLevel": 0,
		"Target": 2,
		"Type": 1,
		"EffectInfos": [],
		"innerName": "Double Kick",
		"Category": 2,
		"MustHit": false
	},
	{
		"MoveID": 33,
		"Accuracy": 100,
		"Power": 5,
		"PP": 35,
		"Priority": 0,
		"CriticalLevel": 0,
		"Target": 2,
		"Type": 0,
		"EffectInfos": [{
			"EffectID":5,
			"EffectChance":100,
			"TargetType":2
		}],
		"innerName": "Tackle",
		"Category": 2,
		"MustHit": false
	},
	{
		"MoveID": 40,
		"Accuracy": 100,
		"Power": 15,
		"PP": 35,
		"Priority": 0,
		"CriticalLevel": 0,
		"Target": 2,
		"Type": 3,
		"EffectInfos": [],
		"innerName": "Poison Sting",
		"Category": 2,
		"MustHit": false
	},
	{
		"MoveID": 52,
		"Accuracy": 100,
		"Power": 40,
		"PP": 25,
		"Priority": 0,
		"CriticalLevel": 0,
		"Target": 2,
		"Type": 9,
		"EffectInfos": [],
		"innerName": "Ember",
		"Category": 3,
		"MustHit": false
	},
	{
		"MoveID": 53,
		"Accuracy": 100,
		"Power": 90,
		"PP": 15,
		"Priority": 0,
		"CriticalLevel": 0,
		"Target": 2,
		"Type": 12,
		"EffectInfos": [{
			"EffectID" : 5,
			"EffectChance": 10,
			"TargetType":2
		}],
		"innerName": "Thunderbolt",
		"Category": 3,
		"MustHit": false
	},
	{
		"MoveID": 55,
		"Accuracy": 100,
		"Power": 40,
		"PP": 25,
		"Priority": 0,
		"CriticalLevel": 0,
		"Target": 2,
		"Type": 10,
		"EffectInfos": [],
		"innerName": "Water Gun",
		"Category": 3,
		"MustHit": false
	},
	{
		"MoveID": 68,
		"Accuracy": 100,
		"Power": 0,
		"PP": 20,
		"Priority": -5,
		"CriticalLevel": 0,
		"Target": 2,
		"Type": 12,
		"EffectInfos": [],
		"innerName": "Counter",
		"Category": 2,
		"MustHit": false
	},
	{
		"MoveID": 243,
		"Accuracy": 40,
		"Power": 100,
		"PP": 30,
		"Priority": 0,
		"CriticalLevel": 0,
		"Target": 2,
		"Type": 12,
		"EffectInfos": [],
		"innerName": "Mirror Coat",
		"Category": 3,
		"MustHit": false
	}
]